aioscrape/__init__.py
aioscrape/middleware.py
aioscrape/utils.py
aioscrape/version.py
aioscrape-0.0.2.dist-info/DESCRIPTION.rst
aioscrape-0.0.2.dist-info/LICENSE.txt
aioscrape-0.0.2.dist-info/METADATA
aioscrape-0.0.2.dist-info/RECORD
aioscrape-0.0.2.dist-info/WHEEL
aioscrape-0.0.2.dist-info/metadata.json
aioscrape-0.0.2.dist-info/top_level.txt
