Metadata-Version: 2.0
Name: aioscrape
Version: 0.0.2
Summary: Async scraping library
Home-page: http://github.com/Suor/aioscrape
Author: Alexander Schepanovski
Author-email: suor.web@gmail.com
License: BSD
Platform: UNKNOWN
Classifier: Development Status :: 3 - Alpha
Classifier: License :: OSI Approved :: BSD License
Classifier: Operating System :: OS Independent
Classifier: Programming Language :: Python
Classifier: Programming Language :: Python :: 3
Classifier: Programming Language :: Python :: 3.6
Classifier: Programming Language :: Python :: Implementation :: CPython
Classifier: Topic :: Software Development :: Libraries :: Python Modules
Classifier: Intended Audience :: Developers
Requires-Dist: aiohttp (>=3.5.4)
Requires-Dist: parsechain (>=0.0.3)
Requires-Dist: funcy (<2.0,>=1.11)
Requires-Dist: aiocontextvars; python_version < "3.7"
Provides-Extra: cache
Requires-Dist: aiocache; extra == 'cache'
Requires-Dist: aiofilecache; extra == 'cache'
